WhatsPy-0.0.3.data/scripts/whatspy
WhatsPy-0.0.3.data/scripts/whatspy.sh
whatspy/__init__.py
whatspy/chrome.py
whatspy/main.py
WhatsPy-0.0.3.dist-info/METADATA
WhatsPy-0.0.3.dist-info/WHEEL
WhatsPy-0.0.3.dist-info/top_level.txt
WhatsPy-0.0.3.dist-info/RECORD
