Metadata-Version: 2.1
Name: WhatsPy
Version: 0.0.3
Summary: Python Whatsapp API based on Selenium and ChromeDriver
Home-page: https://github.com/matheusvanzan/whatspy
Author: Matheus Vanzan
Author-email: matheusvnzn@gmail.com
License: UNKNOWN
Platform: UNKNOWN
Classifier: Programming Language :: Python :: 3
Classifier: License :: OSI Approved :: MIT License
Classifier: Operating System :: OS Independent
